[
  {
    "id": 1,
    "name": "Reymond Julio",
    "username": "reymond",
    "avatarURL": "/avatars/reymond.jpg",
    "coverURL": "/cover/reymond-cover.jpg",
    "age": 26,
    "mutualFriends": 5,
    "isConfirmed": true
  },
  {
    "id": 2,
    "name": "M Haidar Hanif",
    "username": "Haidar",
    "avatarURL": "/avatars/haidar.jpg",
    "coverURL": "/cover/haidar-cover.jpg",
    "age": 30,
    "mutualFriends": 3,
    "isConfirmed": false
  },
  {
    "id": 3,
    "name": "Christopher Kevin",
    "username": "Christopher",
    "avatarURL": "/avatars/christopher.jpg",
    "coverURL": "/cover/christopher-cover.jpg",
    "age": 29,
    "mutualFriends": 6,
    "isConfirmed": false
  },
  {
    "id": 4,
    "name": "Caroline Elizabeth",
    "username": "Caroline",
    "avatarURL": "/avatars/caroline.jpg",
    "coverURL": "/cover/caroline-cover.jpg",
    "age": 25,
    "mutualFriends": 10,
    "isConfirmed": true
  },
  {
    "id": 5,
    "name": "Daniel William",
    "username": "Daniel",
    "avatarURL": "/avatars/daniel.jpg",
    "coverURL": "/cover/daniel-cover.jpg",
    "age": 25,
    "mutualFriends": 8,
    "isConfirmed": true
  },
  {
    "id": 6,
    "name": "Victoria Grace",
    "username": "Daniel",
    "avatarURL": "/avatars/victoria.jpg",
    "coverURL": "/cover/victoria-cover.jpg",
    "age": 28,
    "mutualFriends": 7,
    "isConfirmed": false
  },
  {
    "id": 7,
    "name": "Jessica Lyn",
    "username": "Jessica",
    "avatarURL": "/avatars/jessica.jpg",
    "coverURL": "/cover/jessica-cover.jpg",
    "age": 26,
    "mutualFriends": 9,
    "isConfirmed": true
  },
  {
    "id": 8,
    "name": "Kelly Marie",
    "username": "Kelly",
    "avatarURL": "/avatars/kelly.jpg",
    "coverURL": "/cover/kelly-cover.jpg",
    "age": 26,
    "mutualFriends": 12,
    "isConfirmed": false
  }
]
